UALFparser/Parser.py
UALFparser/__init__.py
parseUALF-0.0.1.dist-info/LICENSE
parseUALF-0.0.1.dist-info/METADATA
parseUALF-0.0.1.dist-info/WHEEL
parseUALF-0.0.1.dist-info/top_level.txt
parseUALF-0.0.1.dist-info/RECORD
