Metadata-Version: 2.1
Name: parseUALF
Version: 0.0.1
Summary: Python class that allows for a python requests response received in the universal ascii lightning format to be parsed to a pandas dataframe object.
Home-page: https://github.com/hildeha/UAFL_dataframe_parser
Author: Hilde Haland
Author-email: hilde.tveit.haland@gmail.com
License: UNKNOWN
Platform: UNKNOWN
Classifier: Programming Language :: Python :: 3
Classifier: License :: OSI Approved :: MIT License
Classifier: Operating System :: OS Independent
Requires-Python: >=3.6
License-File: LICENSE
Requires-Dist: requests (>=2.26.0)
Requires-Dist: pandas (>=1.0.0)
Requires-Dist: numpy (>=1.0.0)
Requires-Dist: plotly (>=5.2.1)
